sallmon/__init__.py
sallmon/test-msg.py
sallmon/cli/__init__.py
sallmon/cli/main.py
sallmon/cli/sallmond.py
sallmon/cli/commands/__init__.py
sallmon/frontend/__init__.py
sallmon/frontend/models.py
sallmon/frontend/server.py
sallmon/frontend/start.py
sallmon/frontend/routes/__init__.py
sallmon/frontend/routes/blocks.py
sallmon/frontend/routes/metrics.py
sallmon/frontend/routes/mining.py
sallmon/frontend/routes/node.py
sallmon/frontend/routes/peers.py
sallmon/frontend/routes/wallets.py
sallmon/frontend/static/assets/05168367a66d9ab6df08b83b847d895e77.png
sallmon/frontend/static/assets/498563dc5c38eba68af3d1c70998467b0d.png
sallmon/frontend/static/assets/b6c13aecb03546076b564a59d40fd30009.png
sallmon/frontend/static/assets/e9d4755cb384120e3ecfd8b7d5913a4f9c.png
sallmon/frontend/static/assets/metrics-meme.gif
sallmon/frontend/static/assets/mining-meme.gif
sallmon/frontend/static/assets/node-control-meme.gif
sallmon/frontend/static/assets/peers-meme.gif
sallmon/frontend/static/assets/wallets-meme.gif
sallmon/frontend/templates/base.html
sallmon/frontend/templates/home.html
sallmon/frontend/templates/metrics.html
sallmon/frontend/templates/mine.html
sallmon/frontend/templates/node_dashboard.html
sallmon/frontend/templates/peers.html
sallmon/frontend/templates/wallet.html
sallmon/frontend/templates/wallet_detail.html
sallmon/frontend/templates/wallets.html
sallmon/sallmon_core/__init__.py
sallmon/sallmon_core/pow-block-test.py
sallmon/sallmon_core/server.py
sallmon/sallmon_core/websocket_server.py
sallmon/sallmon_core/routes/__init__.py
sallmon/sallmon_core/routes/api.py
sallmon/sallmon_core/routes/blocks.py
sallmon/sallmon_core/routes/mempool.py
sallmon/sallmon_core/routes/mine.py
sallmon/sallmon_core/routes/peers.py
sallmon/sallmon_core/routes/utxo.py
sallmon/sallmon_core/routes/wallet.py
sallmon/sallmon_core/routes/websocket.py
sallmon/sallmon_core/services/__init__.py
sallmon/sallmon_core/services/block_db.py
sallmon/sallmon_core/services/blocks.py
sallmon_core-2.4.1.dist-info/LICENSE
sallmon_core-2.4.1.dist-info/METADATA
sallmon_core-2.4.1.dist-info/WHEEL
sallmon_core-2.4.1.dist-info/entry_points.txt
sallmon_core-2.4.1.dist-info/top_level.txt
sallmon_core-2.4.1.dist-info/RECORD
