Metadata-Version: 2.1
Name: sallmon-core
Version: 2.4.1
Summary: Sallmon Core: a utility chain invented to eat Stripe's lunch
Home-page: https://github.com/minakilabs/sallmon_core
Author: c80129b (Andrew Polykandriotis)
Author-email: andrew@minakilabs.com
License: UNKNOWN
Platform: UNKNOWN
Classifier: Programming Language :: Python :: 3.10
Classifier: License :: OSI Approved :: MIT License
Classifier: Operating System :: OS Independent
Requires-Python: >=3.8
Requires-Dist: Pillow
Requires-Dist: click>=8.1.3
Requires-Dist: cryptography
Requires-Dist: fastapi
Requires-Dist: flask>=3.0.0
Requires-Dist: gunicorn
Requires-Dist: httpx
Requires-Dist: uvicorn
Requires-Dist: websockets
